kammanta/__init__.py
kammanta/__main__.py
kammanta/do_timer.py
kammanta/exception_handling.py
kammanta/glob.py
kammanta/gtd_info.py
kammanta/model.py
kammanta/shared_timer.py
kammanta/gui/__init__.py
kammanta/gui/contacts_agendas_tc.py
kammanta/gui/focus_direction_tc.py
kammanta/gui/inbox_tickler_tc.py
kammanta/gui/main_window.py
kammanta/gui/nas_prjs_tc.py
kammanta/gui/reference_search_tc.py
kammanta/widgets/__init__.py
kammanta/widgets/alt_treewidget_checklist_cw.py
kammanta/widgets/calendar_input_dlg.py
kammanta/widgets/checklist_cw.py
kammanta/widgets/done_wid.py
kammanta/widgets/file_list_cw.py
kammanta/widgets/focus_dlg.py
kammanta/widgets/input_cw.py
kammanta/widgets/md_display_dlg.py
kammanta/widgets/md_input_dlg.py
kammanta/widgets/path_sel_dlg.py
kammanta/widgets/processing_wid.py
kammanta/widgets/ref_file_selection_dlg.py
kammanta/widgets/to_reference_dlg.py
kammanta-1.0.11a0.dist-info/LICENSE
kammanta-1.0.11a0.dist-info/METADATA
kammanta-1.0.11a0.dist-info/WHEEL
kammanta-1.0.11a0.dist-info/entry_points.txt
kammanta-1.0.11a0.dist-info/top_level.txt
kammanta-1.0.11a0.dist-info/RECORD
