Metadata-Version: 2.1
Name: kammanta
Version: 1.0.11a0
Summary: A productivity and life organizing application where data is stored as text files and directories
Home-page: https://gitlab.com/SunyataZero/kammanta
Author: Tord Dellsén
Author-email: tord.dellsen@gmail.com
License: GPLv3
Platform: UNKNOWN
Classifier: License :: OSI Approved :: GNU General Public License v3 (GPLv3)
Classifier: Programming Language :: Python
Classifier: Programming Language :: Python :: 3
Classifier: Programming Language :: Python :: 3.8
Classifier: Topic :: Other/Nonlisted Topic
Classifier: Development Status :: 2 - Pre-Alpha
Classifier: Intended Audience :: End Users/Desktop
Requires-Python: >=3.8.0
Requires-Dist: PyQt5 (>=5.14)
